datapath/__init__.py
datapath/_base.py
datapath/collection.py
datapath/folding.py
datapath/format.py
datapath/types.py
python_datapath-0.2.0.dist-info/LICENSE.txt
python_datapath-0.2.0.dist-info/METADATA
python_datapath-0.2.0.dist-info/WHEEL
python_datapath-0.2.0.dist-info/top_level.txt
python_datapath-0.2.0.dist-info/RECORD
