Metadata-Version: 2.1
Name: python-datapath
Version: 0.2.0
Summary: Functions for working with dotted and square-bracketed paths against a recursive dict/list structure
Home-page: https://github.com/ashafer01/python-datapath
Author: Alex Shafer
Author-email: ashafer@pm.me
License: MIT
Requires-Python: >=3.10.0
License-File: LICENSE.txt
Requires-Dist: regex
